{
  "queue": [
    {
      "type": "Other",
      "length_minutes": 4.0,
      "name": "Cycle 1",
      "note": "Other 4min  # Activation",
      "concentration_value": null,
      "concentration_units": "nM",
      "units": "nM",
      "concentrations": {},
      "cycle_id": 2,
      "timestamp": 1769950259.8358452,
      "cycle_num": 1,
      "total_cycles": 0,
      "status": "pending",
      "sensorgram_time": null,
      "end_time_sensorgram": null,
      "delta_spr": null,
      "flags": []
    },
    {
      "type": "Regeneration",
      "length_minutes": 0.5,
      "name": "Cycle 2",
      "note": "Other 30sec  # Wash",
      "concentration_value": null,
      "concentration_units": "nM",
      "units": "nM",
      "concentrations": {},
      "cycle_id": 3,
      "timestamp": 1769950259.8358452,
      "cycle_num": 2,
      "total_cycles": 0,
      "status": "pending",
      "sensorgram_time": null,
      "end_time_sensorgram": null,
      "delta_spr": null,
      "flags": []
    },
    {
      "type": "Immobilization",
      "length_minutes": 4.0,
      "name": "Cycle 3",
      "note": "Immobilization 4min [A]",
      "concentration_value": null,
      "concentration_units": "nM",
      "units": "nM",
      "concentrations": {},
      "cycle_id": 4,
      "timestamp": 1769950259.8358452,
      "cycle_num": 3,
      "total_cycles": 0,
      "status": "pending",
      "sensorgram_time": null,
      "end_time_sensorgram": null,
      "delta_spr": null,
      "flags": []
    },
    {
      "type": "Regeneration",
      "length_minutes": 0.5,
      "name": "Cycle 4",
      "note": "Other 30sec  # Wash",
      "concentration_value": null,
      "concentration_units": "nM",
      "units": "nM",
      "concentrations": {},
      "cycle_id": 5,
      "timestamp": 1769950259.8358452,
      "cycle_num": 4,
      "total_cycles": 0,
      "status": "pending",
      "sensorgram_time": null,
      "end_time_sensorgram": null,
      "delta_spr": null,
      "flags": []
    },
    {
      "type": "Other",
      "length_minutes": 4.0,
      "name": "Cycle 5",
      "note": "Other 4min  # Blocking",
      "concentration_value": null,
      "concentration_units": "nM",
      "units": "nM",
      "concentrations": {},
      "cycle_id": 6,
      "timestamp": 1769950259.8358452,
      "cycle_num": 5,
      "total_cycles": 0,
      "status": "pending",
      "sensorgram_time": null,
      "end_time_sensorgram": null,
      "delta_spr": null,
      "flags": []
    },
    {
      "type": "Regeneration",
      "length_minutes": 0.5,
      "name": "Cycle 6",
      "note": "Other 30sec  # Wash",
      "concentration_value": null,
      "concentration_units": "nM",
      "units": "nM",
      "concentrations": {},
      "cycle_id": 7,
      "timestamp": 1769950259.8358452,
      "cycle_num": 6,
      "total_cycles": 0,
      "status": "pending",
      "sensorgram_time": null,
      "end_time_sensorgram": null,
      "delta_spr": null,
      "flags": []
    },
    {
      "type": "Baseline",
      "length_minutes": 15.0,
      "name": "Cycle 7",
      "note": "Baseline 15min [ALL]",
      "concentration_value": null,
      "concentration_units": "nM",
      "units": "nM",
      "concentrations": {},
      "cycle_id": 8,
      "timestamp": 1769950259.8358452,
      "cycle_num": 7,
      "total_cycles": 0,
      "status": "pending",
      "sensorgram_time": null,
      "end_time_sensorgram": null,
      "delta_spr": null,
      "flags": []
    },
    {
      "type": "Concentration",
      "length_minutes": 5.0,
      "name": "Cycle 8",
      "note": "# Concentration series",
      "concentration_value": null,
      "concentration_units": "nM",
      "units": "nM",
      "concentrations": {},
      "cycle_id": 9,
      "timestamp": 1769950259.8358452,
      "cycle_num": 8,
      "total_cycles": 0,
      "status": "pending",
      "sensorgram_time": null,
      "end_time_sensorgram": null,
      "delta_spr": null,
      "flags": []
    },
    {
      "type": "Concentration",
      "length_minutes": 15.0,
      "name": "Cycle 9",
      "note": "Concentration 15min [A]  # Concentration 1",
      "concentration_value": null,
      "concentration_units": "nM",
      "units": "nM",
      "concentrations": {},
      "cycle_id": 10,
      "timestamp": 1769950259.8358452,
      "cycle_num": 9,
      "total_cycles": 0,
      "status": "pending",
      "sensorgram_time": null,
      "end_time_sensorgram": null,
      "delta_spr": null,
      "flags": []
    },
    {
      "type": "Regeneration",
      "length_minutes": 2.0,
      "name": "Cycle 10",
      "note": "Regeneration 2min [ALL]",
      "concentration_value": null,
      "concentration_units": "nM",
      "units": "nM",
      "concentrations": {},
      "cycle_id": 11,
      "timestamp": 1769950259.8358452,
      "cycle_num": 10,
      "total_cycles": 0,
      "status": "pending",
      "sensorgram_time": null,
      "end_time_sensorgram": null,
      "delta_spr": null,
      "flags": []
    },
    {
      "type": "Baseline",
      "length_minutes": 2.0,
      "name": "Cycle 11",
      "note": "Baseline 2min [ALL]",
      "concentration_value": null,
      "concentration_units": "nM",
      "units": "nM",
      "concentrations": {},
      "cycle_id": 12,
      "timestamp": 1769950259.8358452,
      "cycle_num": 11,
      "total_cycles": 0,
      "status": "pending",
      "sensorgram_time": null,
      "end_time_sensorgram": null,
      "delta_spr": null,
      "flags": []
    },
    {
      "type": "Concentration",
      "length_minutes": 15.0,
      "name": "Cycle 12",
      "note": "Concentration 15min [A]  # Concentration 2",
      "concentration_value": null,
      "concentration_units": "nM",
      "units": "nM",
      "concentrations": {},
      "cycle_id": 13,
      "timestamp": 1769950259.8358452,
      "cycle_num": 12,
      "total_cycles": 0,
      "status": "pending",
      "sensorgram_time": null,
      "end_time_sensorgram": null,
      "delta_spr": null,
      "flags": []
    },
    {
      "type": "Regeneration",
      "length_minutes": 2.0,
      "name": "Cycle 13",
      "note": "Regeneration 2min [ALL]",
      "concentration_value": null,
      "concentration_units": "nM",
      "units": "nM",
      "concentrations": {},
      "cycle_id": 14,
      "timestamp": 1769950259.8358452,
      "cycle_num": 13,
      "total_cycles": 0,
      "status": "pending",
      "sensorgram_time": null,
      "end_time_sensorgram": null,
      "delta_spr": null,
      "flags": []
    },
    {
      "type": "Baseline",
      "length_minutes": 2.0,
      "name": "Cycle 14",
      "note": "Baseline 2min [ALL]",
      "concentration_value": null,
      "concentration_units": "nM",
      "units": "nM",
      "concentrations": {},
      "cycle_id": 15,
      "timestamp": 1769950259.8358452,
      "cycle_num": 14,
      "total_cycles": 0,
      "status": "pending",
      "sensorgram_time": null,
      "end_time_sensorgram": null,
      "delta_spr": null,
      "flags": []
    },
    {
      "type": "Concentration",
      "length_minutes": 15.0,
      "name": "Cycle 15",
      "note": "Concentration 15min [A]  # Concentration 3",
      "concentration_value": null,
      "concentration_units": "nM",
      "units": "nM",
      "concentrations": {},
      "cycle_id": 16,
      "timestamp": 1769950259.8358452,
      "cycle_num": 15,
      "total_cycles": 0,
      "status": "pending",
      "sensorgram_time": null,
      "end_time_sensorgram": null,
      "delta_spr": null,
      "flags": []
    },
    {
      "type": "Regeneration",
      "length_minutes": 2.0,
      "name": "Cycle 16",
      "note": "Regeneration 2min [ALL]",
      "concentration_value": null,
      "concentration_units": "nM",
      "units": "nM",
      "concentrations": {},
      "cycle_id": 17,
      "timestamp": 1769950259.8358452,
      "cycle_num": 16,
      "total_cycles": 0,
      "status": "pending",
      "sensorgram_time": null,
      "end_time_sensorgram": null,
      "delta_spr": null,
      "flags": []
    },
    {
      "type": "Baseline",
      "length_minutes": 2.0,
      "name": "Cycle 17",
      "note": "Baseline 2min [ALL]",
      "concentration_value": null,
      "concentration_units": "nM",
      "units": "nM",
      "concentrations": {},
      "cycle_id": 18,
      "timestamp": 1769950259.8358452,
      "cycle_num": 17,
      "total_cycles": 0,
      "status": "pending",
      "sensorgram_time": null,
      "end_time_sensorgram": null,
      "delta_spr": null,
      "flags": []
    }
  ],
  "completed": [
    {
      "type": "Baseline",
      "length_minutes": 0.5,
      "name": "Cycle 1",
      "note": "Baseline 30sec [ALL]",
      "concentration_value": null,
      "concentration_units": "nM",
      "units": "nM",
      "concentrations": {},
      "cycle_id": 1,
      "timestamp": 1769950259.8358452,
      "cycle_num": 1,
      "total_cycles": 18,
      "status": "running",
      "sensorgram_time": 0.0,
      "end_time_sensorgram": null,
      "delta_spr": null,
      "flags": []
    }
  ],
  "cycle_counter": 18,
  "timestamp": 1769950278.853631
}