{
  "detector_serial": "FLMT05242",
  "timestamp": "20260117_090048",
  "model_type": "3-stage-linear",
  "model_equation": "counts = slope_10ms \u00d7 intensity \u00d7 (time_ms / 10)",
  "integration_times": [
    10,
    20,
    30,
    45,
    60
  ],
  "dark_counts_per_time": {
    "10": 2751.5607886089815,
    "20": 2771.6074124507854,
    "30": 2788.4207098664933,
    "45": 2825.2806311240042,
    "60": 2849.8539119623456
  },
  "led_models": {
    "A": [
      {
        "time_ms": 10,
        "slope": -0.027483274621829965
      },
      {
        "time_ms": 20,
        "slope": 0.0544276615059775
      },
      {
        "time_ms": 30,
        "slope": 0.26263428742891076
      },
      {
        "time_ms": 45,
        "slope": 0.42115546393750347
      },
      {
        "time_ms": 60,
        "slope": 1.023455591407398
      }
    ],
    "B": [
      {
        "time_ms": 10,
        "slope": -0.008468235877876937
      },
      {
        "time_ms": 20,
        "slope": 0.07425873025270936
      },
      {
        "time_ms": 30,
        "slope": 0.30657813294723774
      },
      {
        "time_ms": 45,
        "slope": 0.4553111485477385
      },
      {
        "time_ms": 60,
        "slope": 1.0024487675966305
      }
    ],
    "C": [
      {
        "time_ms": 10,
        "slope": 0.015412189297729107
      },
      {
        "time_ms": 20,
        "slope": 0.10475977620556186
      },
      {
        "time_ms": 30,
        "slope": 0.3412139175419535
      },
      {
        "time_ms": 45,
        "slope": 0.6195053432402863
      },
      {
        "time_ms": 60,
        "slope": 1.395699644681022
      }
    ],
    "D": [
      {
        "time_ms": 10,
        "slope": 29.673314387772212
      },
      {
        "time_ms": 20,
        "slope": 59.78041800758668
      },
      {
        "time_ms": 30,
        "slope": 90.01610164132069
      },
      {
        "time_ms": 45,
        "slope": 135.4706160536719
      },
      {
        "time_ms": 60,
        "slope": 177.59498061040227
      }
    ]
  },
  "training_method": "automatic_oem_workflow",
  "detector_wait_ms": 50
}